LICENSE
README.md
pyproject.toml
setup.py
doctr/__init__.py
doctr/file_utils.py
doctr/version.py
doctr/datasets/__init__.py
doctr/datasets/cord.py
doctr/datasets/detection.py
doctr/datasets/doc_artefacts.py
doctr/datasets/funsd.py
doctr/datasets/ic03.py
doctr/datasets/ic13.py
doctr/datasets/iiit5k.py
doctr/datasets/imgur5k.py
doctr/datasets/indicData.py
doctr/datasets/loader.py
doctr/datasets/mjsynth.py
doctr/datasets/ocr.py
doctr/datasets/recognition.py
doctr/datasets/sroie.py
doctr/datasets/svhn.py
doctr/datasets/svt.py
doctr/datasets/synthtext.py
doctr/datasets/utils.py
doctr/datasets/vocabs.py
doctr/datasets/datasets/__init__.py
doctr/datasets/datasets/base.py
doctr/datasets/datasets/pytorch.py
doctr/datasets/datasets/tensorflow.py
doctr/datasets/generator/__init__.py
doctr/datasets/generator/base.py
doctr/datasets/generator/pytorch.py
doctr/datasets/generator/tensorflow.py
doctr/io/__init__.py
doctr/io/elements.py
doctr/io/html.py
doctr/io/pdf.py
doctr/io/reader.py
doctr/io/image/__init__.py
doctr/io/image/base.py
doctr/io/image/pytorch.py
doctr/io/image/tensorflow.py
doctr/models/__init__.py
doctr/models/_utils.py
doctr/models/builder.py
doctr/models/core.py
doctr/models/zoo.py
doctr/models/artefacts/__init__.py
doctr/models/artefacts/barcode.py
doctr/models/artefacts/face.py
doctr/models/classification/__init__.py
doctr/models/classification/zoo.py
doctr/models/classification/magc_resnet/__init__.py
doctr/models/classification/magc_resnet/pytorch.py
doctr/models/classification/magc_resnet/tensorflow.py
doctr/models/classification/mobilenet/__init__.py
doctr/models/classification/mobilenet/pytorch.py
doctr/models/classification/mobilenet/tensorflow.py
doctr/models/classification/predictor/__init__.py
doctr/models/classification/predictor/pytorch.py
doctr/models/classification/predictor/tensorflow.py
doctr/models/classification/resnet/__init__.py
doctr/models/classification/resnet/pytorch.py
doctr/models/classification/resnet/tensorflow.py
indic_doctr.egg-info/PKG-INFO
indic_doctr.egg-info/SOURCES.txt
indic_doctr.egg-info/dependency_links.txt
indic_doctr.egg-info/requires.txt
indic_doctr.egg-info/top_level.txt
indic_doctr.egg-info/zip-safe