Metadata-Version: 2.1
Name: indic-doctr
Version: 0.7.1a0
Summary: Indic Document Text Recognition (indic-docTR): deep Learning for high-performance OCR on documents.
Author-email: Mindee <contact@mindee.com>
Maintainer: François-Guillaume Fernandez, Charles Gaillard
License:                                  Apache License
Project-URL: documentation, https://mindee.github.io/doctr
Project-URL: repository, https://github.com/mindee/doctr
Project-URL: tracker, https://github.com/mindee/doctr/issues
Project-URL: changelog, https://github.com/mindee/doctr/latest/changelog.html
Keywords: OCR,deep learning,computer vision,tensorflow,pytorch,text detection,text recognition
Classifier: Development Status :: 4 - Beta
Classifier: Intended Audience :: Developers
Classifier: Intended Audience :: Education
Classifier: Intended Audience :: Science/Research
Classifier: License :: OSI Approved :: Apache Software License
Classifier: Natural Language :: English
Classifier: Operating System :: OS Independent
Classifier: Programming Language :: Python :: 3
Classifier: Programming Language :: Python :: 3.6
Classifier: Programming Language :: Python :: 3.7
Classifier: Programming Language :: Python :: 3.8
Classifier: Topic :: Scientific/Engineering :: Artificial Intelligence
Requires-Python: <4,>=3.6.0
Provides-Extra: tf
Provides-Extra: torch
Provides-Extra: testing
Provides-Extra: quality
Provides-Extra: docs
Provides-Extra: dev
License-File: LICENSE
